{
  "label": "llama8b_t02_s456_informative_v2_logitlens",
  "enriched_log": "logs/cot_llama8b_t02_s456_informative_v2_logitlens_enriched.jsonl",
  "logit_lens_sidecar": "logs/cot_llama8b_t02_s456_informative_v2_logitlens_logit_lens.jsonl",
  "stats": {
    "enriched_decisions_seen": 519,
    "enriched_decisions_with_action_metadata": 311,
    "sidecar_records_loaded": 311,
    "joined_records": 311,
    "unmatched_enriched": 208
  },
  "buckets": {
    "clean": {
      "n_decisions": 290,
      "n_with_logit_lens": 290,
      "num_layers": 32,
      "per_layer_action_fraction": [
        {
          "OTHER": 1.0
        },
        {
          "OTHER": 1.0
        },
        {
          "OTHER": 1.0
        },
        {
          "OTHER": 1.0
        },
        {
          "OTHER": 1.0
        },
        {
          "OTHER": 1.0
        },
        {
          "OTHER": 1.0
        },
        {
          "OTHER": 1.0
        },
        {
          "OTHER": 1.0
        },
        {
          "OTHER": 1.0
        },
        {
          "OTHER": 1.0
        },
        {
          "OTHER": 1.0
        },
        {
          "OTHER": 1.0
        },
        {
          "OTHER": 1.0
        },
        {
          "OTHER": 1.0
        },
        {
          "OTHER": 1.0
        },
        {
          "OTHER": 1.0
        },
        {
          "OTHER": 1.0
        },
        {
          "OTHER": 1.0
        },
        {
          "OTHER": 1.0
        },
        {
          "OTHER": 1.0
        },
        {
          "OTHER": 1.0
        },
        {
          "OTHER": 1.0
        },
        {
          "OTHER": 1.0
        },
        {
          "OTHER": 1.0
        },
        {
          "OTHER": 1.0
        },
        {
          "OTHER": 1.0
        },
        {
          "OTHER": 1.0
        },
        {
          "OTHER": 1.0
        },
        {
          "OTHER": 1.0
        },
        {
          "OTHER": 1.0
        },
        {
          "OTHER": 1.0
        }
      ],
      "per_layer_mean_entropy": [
        9.3769,
        9.2601,
        9.2717,
        9.3381,
        9.2506,
        9.3368,
        9.3359,
        9.3457,
        9.3604,
        9.4129,
        9.4615,
        9.4678,
        9.5081,
        9.3392,
        9.3565,
        9.2851,
        9.2128,
        8.7953,
        8.3759,
        7.9473,
        6.939,
        6.469,
        5.9772,
        5.1513,
        4.444,
        3.6015,
        3.3633,
        2.8826,
        2.5515,
        2.0649,
        1.4796,
        1.0266
      ],
      "crystallization_layer": null
    },
    "illegal_fold": {
      "n_decisions": 21,
      "n_with_logit_lens": 21,
      "num_layers": 32,
      "per_layer_action_fraction": [
        {
          "OTHER": 1.0
        },
        {
          "OTHER": 1.0
        },
        {
          "OTHER": 1.0
        },
        {
          "OTHER": 1.0
        },
        {
          "OTHER": 1.0
        },
        {
          "OTHER": 1.0
        },
        {
          "OTHER": 1.0
        },
        {
          "OTHER": 1.0
        },
        {
          "OTHER": 1.0
        },
        {
          "OTHER": 1.0
        },
        {
          "OTHER": 1.0
        },
        {
          "OTHER": 1.0
        },
        {
          "OTHER": 1.0
        },
        {
          "OTHER": 1.0
        },
        {
          "OTHER": 1.0
        },
        {
          "OTHER": 1.0
        },
        {
          "OTHER": 1.0
        },
        {
          "OTHER": 1.0
        },
        {
          "OTHER": 1.0
        },
        {
          "OTHER": 1.0
        },
        {
          "OTHER": 1.0
        },
        {
          "OTHER": 1.0
        },
        {
          "OTHER": 1.0
        },
        {
          "OTHER": 1.0
        },
        {
          "OTHER": 1.0
        },
        {
          "OTHER": 1.0
        },
        {
          "OTHER": 1.0
        },
        {
          "OTHER": 1.0
        },
        {
          "OTHER": 1.0
        },
        {
          "OTHER": 1.0
        },
        {
          "OTHER": 1.0
        },
        {
          "OTHER": 1.0
        }
      ],
      "per_layer_mean_entropy": [
        9.345,
        9.2248,
        9.222,
        9.2967,
        9.2068,
        9.3191,
        9.3244,
        9.3025,
        9.2404,
        9.3321,
        9.405,
        9.4139,
        9.4336,
        9.279,
        9.2968,
        9.2251,
        9.1268,
        8.7734,
        8.3442,
        8.0377,
        7.0796,
        6.5779,
        5.9648,
        5.2595,
        4.5041,
        3.8064,
        3.5714,
        3.061,
        2.6085,
        2.1649,
        1.5691,
        1.0889
      ],
      "crystallization_layer": null
    },
    "illegal_other": {
      "n_decisions": 0,
      "n_with_logit_lens": 0,
      "num_layers": 0,
      "per_layer_action_fraction": [],
      "per_layer_mean_entropy": [],
      "crystallization_layer": null
    },
    "alias_unrecognized": {
      "n_decisions": 0,
      "n_with_logit_lens": 0,
      "num_layers": 0,
      "per_layer_action_fraction": [],
      "per_layer_mean_entropy": [],
      "crystallization_layer": null
    },
    "json_failure": {
      "n_decisions": 208,
      "n_with_logit_lens": 0,
      "num_layers": 0,
      "per_layer_action_fraction": [],
      "per_layer_mean_entropy": [],
      "crystallization_layer": null
    }
  }
}