{
  "label": "ministral8b_t02_s456_informative_v2_logitlens",
  "enriched_log": "logs/cot_ministral8b_t02_s456_informative_v2_logitlens_enriched.jsonl",
  "logit_lens_sidecar": "logs/cot_ministral8b_t02_s456_informative_v2_logitlens_logit_lens.jsonl",
  "stats": {
    "enriched_decisions_seen": 212,
    "enriched_decisions_with_action_metadata": 108,
    "sidecar_records_loaded": 108,
    "joined_records": 108,
    "unmatched_enriched": 104
  },
  "buckets": {
    "clean": {
      "n_decisions": 104,
      "n_with_logit_lens": 104,
      "num_layers": 36,
      "per_layer_action_fraction": [
        {
          "OTHER": 1.0
        },
        {
          "OTHER": 1.0
        },
        {
          "OTHER": 1.0
        },
        {
          "OTHER": 1.0
        },
        {
          "OTHER": 1.0
        },
        {
          "OTHER": 1.0
        },
        {
          "OTHER": 1.0
        },
        {
          "OTHER": 1.0
        },
        {
          "OTHER": 1.0
        },
        {
          "OTHER": 1.0
        },
        {
          "OTHER": 1.0
        },
        {
          "OTHER": 1.0
        },
        {
          "OTHER": 1.0
        },
        {
          "OTHER": 1.0
        },
        {
          "OTHER": 1.0
        },
        {
          "OTHER": 1.0
        },
        {
          "OTHER": 1.0
        },
        {
          "OTHER": 1.0
        },
        {
          "OTHER": 1.0
        },
        {
          "OTHER": 1.0
        },
        {
          "OTHER": 1.0
        },
        {
          "OTHER": 1.0
        },
        {
          "OTHER": 1.0
        },
        {
          "OTHER": 1.0
        },
        {
          "OTHER": 1.0
        },
        {
          "OTHER": 1.0
        },
        {
          "OTHER": 1.0
        },
        {
          "OTHER": 1.0
        },
        {
          "OTHER": 1.0
        },
        {
          "OTHER": 1.0
        },
        {
          "OTHER": 1.0
        },
        {
          "OTHER": 1.0
        },
        {
          "OTHER": 1.0
        },
        {
          "OTHER": 1.0
        },
        {
          "OTHER": 1.0
        },
        {
          "OTHER": 1.0
        }
      ],
      "per_layer_mean_entropy": [
        10.545,
        9.9713,
        10.261,
        10.2126,
        10.3072,
        10.2804,
        10.3524,
        10.1515,
        10.1308,
        10.0859,
        10.3188,
        10.4471,
        10.505,
        10.4526,
        10.4182,
        10.1103,
        10.1245,
        9.988,
        9.682,
        9.2704,
        8.7959,
        8.2485,
        8.4029,
        7.9188,
        7.5571,
        6.7066,
        6.3126,
        6.0953,
        5.5454,
        4.9534,
        4.6509,
        3.6731,
        2.8633,
        2.5721,
        1.2059,
        0.9578
      ],
      "crystallization_layer": null
    },
    "illegal_fold": {
      "n_decisions": 4,
      "n_with_logit_lens": 4,
      "num_layers": 36,
      "per_layer_action_fraction": [
        {
          "OTHER": 1.0
        },
        {
          "OTHER": 1.0
        },
        {
          "OTHER": 1.0
        },
        {
          "OTHER": 1.0
        },
        {
          "OTHER": 1.0
        },
        {
          "OTHER": 1.0
        },
        {
          "OTHER": 1.0
        },
        {
          "OTHER": 1.0
        },
        {
          "OTHER": 1.0
        },
        {
          "OTHER": 1.0
        },
        {
          "OTHER": 1.0
        },
        {
          "OTHER": 1.0
        },
        {
          "OTHER": 1.0
        },
        {
          "OTHER": 1.0
        },
        {
          "OTHER": 1.0
        },
        {
          "OTHER": 1.0
        },
        {
          "OTHER": 1.0
        },
        {
          "OTHER": 1.0
        },
        {
          "OTHER": 1.0
        },
        {
          "OTHER": 1.0
        },
        {
          "OTHER": 1.0
        },
        {
          "OTHER": 1.0
        },
        {
          "OTHER": 1.0
        },
        {
          "OTHER": 1.0
        },
        {
          "OTHER": 1.0
        },
        {
          "OTHER": 1.0
        },
        {
          "OTHER": 1.0
        },
        {
          "OTHER": 1.0
        },
        {
          "OTHER": 1.0
        },
        {
          "OTHER": 1.0
        },
        {
          "OTHER": 1.0
        },
        {
          "OTHER": 1.0
        },
        {
          "OTHER": 1.0
        },
        {
          "OTHER": 1.0
        },
        {
          "OTHER": 1.0
        },
        {
          "OTHER": 1.0
        }
      ],
      "per_layer_mean_entropy": [
        10.4825,
        9.8831,
        10.2185,
        10.2153,
        10.321,
        10.3117,
        10.3418,
        10.2353,
        10.2258,
        10.2003,
        10.38,
        10.5059,
        10.5124,
        10.4672,
        10.4597,
        10.2601,
        10.2445,
        10.149,
        9.8485,
        9.5755,
        9.0784,
        8.5762,
        8.744,
        8.3717,
        8.0082,
        7.3872,
        6.7845,
        6.4254,
        5.7167,
        4.9886,
        4.8444,
        4.1136,
        3.4337,
        2.8095,
        1.5584,
        1.2533
      ],
      "crystallization_layer": null
    },
    "illegal_other": {
      "n_decisions": 0,
      "n_with_logit_lens": 0,
      "num_layers": 0,
      "per_layer_action_fraction": [],
      "per_layer_mean_entropy": [],
      "crystallization_layer": null
    },
    "alias_unrecognized": {
      "n_decisions": 0,
      "n_with_logit_lens": 0,
      "num_layers": 0,
      "per_layer_action_fraction": [],
      "per_layer_mean_entropy": [],
      "crystallization_layer": null
    },
    "json_failure": {
      "n_decisions": 104,
      "n_with_logit_lens": 0,
      "num_layers": 0,
      "per_layer_action_fraction": [],
      "per_layer_mean_entropy": [],
      "crystallization_layer": null
    }
  }
}